mcp_server/__init__.py
mcp_server/mcp_http_server.py
mcp_server/mcp_stdio_server.py
mcp_server/tool_definitions.py
mcp_server/tool_registry.py
mcp_server/core/__init__.py
mcp_server/core/server.py
mcp_server/core/tool_registry.py
mcp_server/examples/classic_problems.py
mcp_server/examples/graph_coloring.py
mcp_server/examples/logic_puzzles.py
mcp_server/examples/map_coloring.py
mcp_server/examples/minimax.py
mcp_server/examples/n_queens.py
mcp_server/examples/optimized_csp.py
mcp_server/examples/optimized_lp.py
mcp_server/examples/scheduling.py
mcp_server/examples/scipy_optimization.py
mcp_server/handlers/__init__.py
mcp_server/handlers/file_ops.py
mcp_server/handlers/gurddy.py
mcp_server/middleware/__init__.py
mcp_server/middleware/origin_validator.py
mcp_server/routes/__init__.py
mcp_server/routes/health_routes.py
mcp_server/routes/mcp_routes.py
mcp_server/tools/__init__.py
mcp_server/tools/gurddy_demo.py
mcp_server/tools/gurddy_install.py
mcp_server/tools/list_files.py
mcp_server/tools/registry.py
mcp_server/utils/__init__.py
mcp_server/utils/helpers.py
gurddy_mcp-0.1.11.dist-info/LICENSE
gurddy_mcp-0.1.11.dist-info/METADATA
gurddy_mcp-0.1.11.dist-info/WHEEL
gurddy_mcp-0.1.11.dist-info/entry_points.txt
gurddy_mcp-0.1.11.dist-info/top_level.txt
gurddy_mcp-0.1.11.dist-info/RECORD
