Metadata-Version: 2.1
Name: gurddy_mcp
Version: 0.1.11
Summary: MCP (Model Context Protocol) server for Gurddy optimization library - CSP, LP, and SciPy integration for advanced optimization
Author-email: Gurddy MCP Team <contact@example.com>
Maintainer-email: Gurddy MCP Team <contact@example.com>
License: MIT
Project-URL: Homepage, https://github.com/novvoo/gurddy-mcp
Project-URL: Repository, https://github.com/novvoo/gurddy-mcp.git
Project-URL: Documentation, https://github.com/novvoo/gurddy-mcp#readme
Project-URL: Bug Tracker, https://github.com/novvoo/gurddy-mcp/issues
Project-URL: Live Demo, https://gurddy-mcp.fly.dev
Keywords: mcp,model-context-protocol,optimization,constraint-satisfaction,linear-programming,csp,lp,gurddy,solver,ai-assistant,scipy,nonlinear-optimization,statistical-optimization,signal-processing
Classifier: Development Status :: 4 - Beta
Classifier: Intended Audience :: Developers
Classifier: Intended Audience :: Science/Research
Classifier: Operating System :: OS Independent
Classifier: Programming Language :: Python :: 3
Classifier: Programming Language :: Python :: 3.8
Classifier: Programming Language :: Python :: 3.9
Classifier: Programming Language :: Python :: 3.10
Classifier: Programming Language :: Python :: 3.11
Classifier: Programming Language :: Python :: 3.12
Classifier: Topic :: Scientific/Engineering :: Mathematics
Classifier: Topic :: Software Development :: Libraries :: Python Modules
Classifier: Topic :: System :: Distributed Computing
Requires-Python: >=3.8
License-File: LICENSE
Requires-Dist: fastapi>=0.95.0
Requires-Dist: uvicorn[standard]>=0.22.0
Requires-Dist: requests>=2.0
Requires-Dist: pulp>=2.6.0
Requires-Dist: gurddy>=0.1.8
Requires-Dist: pydantic>=2.0.0
Requires-Dist: scipy>=1.9.0
Requires-Dist: numpy>=1.21.0
Provides-Extra: dev
Requires-Dist: pytest>=7.0.0; extra == "dev"
Requires-Dist: pytest-asyncio>=0.21.0; extra == "dev"
Requires-Dist: black>=23.0.0; extra == "dev"
Requires-Dist: isort>=5.12.0; extra == "dev"
Requires-Dist: flake8>=6.0.0; extra == "dev"
Requires-Dist: mypy>=1.0.0; extra == "dev"
Provides-Extra: test
Requires-Dist: pytest>=7.0.0; extra == "test"
Requires-Dist: pytest-asyncio>=0.21.0; extra == "test"
Requires-Dist: httpx>=0.24.0; extra == "test"
